semaforo/semaforo.v
`timescale 1ns / 1ps
//////////////////////////////////////////////////////////////////////////////////
// Company: 
// Engineer: 
// 
// Create Date:    20:44:13 04/14/2013 
// Design Name: 
// Module Name:    semaforo 
// Project Name: 
// Target Devices: 
// Tool versions: 
// Description: 
// Dependencies: 
//
// Revision: 
// Revision 0.01 - File Created
// Additional Comments: 
//
//////////////////////////////////////////////////////////////////////////////////
module semaforo
#(
	parameter t_largo = 10,
	parameter t_corto = 3
)
(
    input pulsador,
    input clk,
	 input rst,
	 output  rojo,
	 output  amarillo,
	 output  verde,
	 output  blanco
);
	 
localparam E0  = 0 , E1 = 1 , E2  = 2;
reg [1:0] estado ;
//reg [1:0] sig_estado ;
reg regpul; 

reg [3:0] cuenta = 0;
//always @ (estado)
//begin
//	case (estado)
//		E0 : sig_estado <= E1;
//		E1 : sig_estado <= E2;
//		E2 : sig_estado <= E0;
//	endcase
//end	


always @ (posedge clk)
begin
	if (rst) 
	begin
		estado <= E0;
		cuenta <= 0;
		regpul <=0;
	end
	
	else
	begin
		if(pulsador)
			regpul<=1;
		if(cuenta < 10)
			cuenta <= cuenta + 1;
		case (estado)
		E0 : begin 
				if(regpul && cuenta==10)
					begin
					estado <= E1;
					cuenta <= 0;
					end
				end
		E1 : begin 
			if( cuenta==3)
				begin
				estado <= E2;
				cuenta <= 0;
				
				end
				end
		E2 : begin
				if( cuenta==10)
				begin
				estado <= E0;
				cuenta <= 0;
				regpul <= 0;
				end
				end
	endcase

	end
end

assign verde = (estado == E0);
assign amarillo = (estado == E1);
assign rojo = (estado == E2);
assign blanco = (estado == E2);

endmodule

semaforo/test.v
`timescale 1ns / 1ps

////////////////////////////////////////////////////////////////////////////////
// Company: 
// Engineer:
//
// Create Date:   21:51:09 04/14/2013
// Design Name:   semaforo
// Module Name:   Z:/semaforo/test.v
// Project Name:  semaforo
// Target Device:  
// Tool versions:  
// Description: 
//
// Verilog Test Fixture created by ISE for module: semaforo
//
// Dependencies:
// 
// Revision:
// Revision 0.01 - File Created
// Additional Comments:
// 
////////////////////////////////////////////////////////////////////////////////

module test;

	// Inputs
	reg pulsador;
	reg clk;
	reg rst;

	// Outputs
	wire rojo;
	wire amarillo;
	wire verde;
	wire blanco;

	// Instantiate the Unit Under Test (UUT)
	semaforo uut (
		.pulsador(pulsador), 
		.clk(clk), 
		.rst(rst), 
		.rojo(rojo), 
		.amarillo(amarillo), 
		.verde(verde), 
		.blanco(blanco)
	);
   always 
		#10 clk = ~clk;
	initial begin
  $dumpfile ("test.vcd");
  $dumpvars (1, test);
  //$monitor ("clk=%b, rst=%b, pulsador=%b", clk, rst, pulsador);
		// Initialize Inputs
		pulsador = 0;
		clk = 0;
		rst = 0;

		// Wait 100 ns for global reset to finish
		#100;
      #10 rst =1;  
		#10 rst =0;
		// Add stimulus here
  #2000 $finish;
	end
      
endmodule

semaforo/test.vcd
$date
	Mon Apr 15 00:48:44 2013
$end
$version
	Icarus Verilog
$end
$timescale
	1ps
$end
$scope module test $end
$var wire 1 ! amarillo $end
$var wire 1 " blanco $end
$var wire 1 # rojo $end
$var wire 1 $ verde $end
$var reg 1 % clk $end
$var reg 1 & pulsador $end
$var reg 1 ' rst $end
$upscope $end
$enddefinitions $end
#0
$dumpvars
0'
0&
0%
x$
x#
x"
x!
$end
#10000
1%
#20000
0%
#30000
1%
#40000
0%
#50000
1%
#60000
0%
#70000
1%
#80000
0%
#90000
1%
#100000
0%
#110000
1$
0!
0#
0"
1%
1'
#120000
0%
0'
#130000
1%
#140000
0%
#150000
1%
#160000
0%
#170000
1%
#180000
0%
#190000
1%
#200000
0%
#210000
1%
#220000
0%
#230000
1%
#240000
0%
#250000
1%
#260000
0%
#270000
1%
#280000
0%
#290000
1%
#300000
0%
#310000
1%
#320000
0%
#330000
0$
1!
1%
#340000
0%
#350000
1%
#360000
0%
#370000
1%
#380000
0%
#390000
1%
#400000
0%
#410000
0!
1#
1"
1%
#420000
0%
#430000
1%
#440000
0%
#450000
1%
#460000
0%
#470000
1%
#480000
0%
#490000
1%
#500000
0%
#510000
1%
#520000
0%
#530000
1%
#540000
0%
#550000
1%
#560000
0%
#570000
1%
#580000
0%
#590000
1%
#600000
0%
#610000
1%
#620000
0%
#630000
1$
0#
0"
1%
#640000
0%
#650000
1%
#660000
0%
#670000
1%
#680000
0%
#690000
1%
#700000
0%
#710000
1%
#720000
0%
#730000
1%
#740000
0%
#750000
1%
#760000
0%
#770000
1%
#780000
0%
#790000
1%
#800000
0%
#810000
1%
#820000
0%
#830000
1%
#840000
0%
#850000
0$
1!
1%
#860000
0%
#870000
1%
#880000
0%
#890000
1%
#900000
0%
#910000
1%
#920000
0%
#930000
0!
1#
1"
1%
#940000
0%
#950000
1%
#960000
0%
#970000
1%
#980000
0%
#990000
1%
#1000000
0%
#1010000
1%
#1020000
0%
#1030000
1%
#1040000
0%
#1050000
1%
#1060000
0%
#1070000
1%
#1080000
0%
#1090000
1%
#1100000
0%
#1110000
1%
#1120000
0%
#1130000
1%
#1140000
0%
#1150000
1$
0#
0"
1%
#1160000
0%
#1170000
1%
#1180000
0%
#1190000
1%
#1200000
0%
#1210000
1%
#1220000
0%
#1230000
1%
#1240000
0%
#1250000
1%
#1260000
0%
#1270000
1%
#1280000
0%
#1290000
1%
#1300000
0%
#1310000
1%
#1320000
0%
#1330000
1%
#1340000
0%
#1350000
1%
#1360000
0%
#1370000
0$
1!
1%
#1380000
0%
#1390000
1%
#1400000
0%
#1410000
1%
#1420000
0%
#1430000
1%
#1440000
0%
#1450000
0!
1#
1"
1%
#1460000
0%
#1470000
1%
#1480000
0%
#1490000
1%
#1500000
0%
#1510000
1%
#1520000
0%
#1530000
1%
#1540000
0%
#1550000
1%
#1560000
0%
#1570000
1%
#1580000
0%
#1590000
1%
#1600000
0%
#1610000
1%
#1620000
0%
#1630000
1%
#1640000
0%
#1650000
1%
#1660000
0%
#1670000
1$
0#
0"
1%
#1680000
0%
#1690000
1%
#1700000
0%
#1710000
1%
#1720000
0%
#1730000
1%
#1740000
0%
#1750000
1%
#1760000
0%
#1770000
1%
#1780000
0%
#1790000
1%
#1800000
0%
#1810000
1%
#1820000
0%
#1830000
1%
#1840000
0%
#1850000
1%
#1860000
0%
#1870000
1%
#1880000
0%
#1890000
0$
1!
1%
#1900000
0%
#1910000
1%
#1920000
0%
#1930000
1%
#1940000
0%
#1950000
1%
#1960000
0%
#1970000
0!
1#
1"
1%
